<ItemList>
  <Item Name="아이템" Level="1" Critical="0.567558" />
  <Item Name="아이템" Level="1" Critical="0.4626929" />
  <Item Name="아이템" Level="1" Critical="0.7986573" />
  <Item Name="아이템" Level="1" Critical="0.2111336" />
  <Item Name="아이템" Level="1" Critical="0.9384317" />
  <Item Name="아이템" Level="1" Critical="0.9709446" />
  <Item Name="아이템" Level="1" Critical="0.270052" />
  <Item Name="아이템" Level="1" Critical="0.8003919" />
  <Item Name="아이템" Level="1" Critical="0.8264072" />
  <Item Name="아이템" Level="1" Critical="0.3000335" />
</ItemList>